dpi_textract_/__init__.py
dpi_textract_/setup.py
dpitextract_1-0.0.9.dist-info/METADATA
dpitextract_1-0.0.9.dist-info/WHEEL
dpitextract_1-0.0.9.dist-info/RECORD
